main.py
mseep_eagle_mcp_server-0.1.2.dist-info/licenses/LICENSE
mseep_eagle_mcp_server-0.1.2.dist-info/METADATA
mseep_eagle_mcp_server-0.1.2.dist-info/WHEEL
mseep_eagle_mcp_server-0.1.2.dist-info/entry_points.txt
mseep_eagle_mcp_server-0.1.2.dist-info/top_level.txt
mseep_eagle_mcp_server-0.1.2.dist-info/RECORD
